icekit_press_releases-0.81.dist-info/DESCRIPTION.rst
icekit_press_releases-0.81.dist-info/METADATA
icekit_press_releases-0.81.dist-info/RECORD
icekit_press_releases-0.81.dist-info/WHEEL
icekit_press_releases-0.81.dist-info/metadata.json
icekit_press_releases-0.81.dist-info/top_level.txt
press_releases/__init__.py
press_releases/admin.py
press_releases/apps.py
press_releases/models.py
press_releases/page_type_plugins.py
press_releases/search_indexes.py
press_releases/migrations/0001_initial.py
press_releases/migrations/0002_auto_20160810_1832.py
press_releases/migrations/0003_auto_20160810_1856.py
press_releases/migrations/0004_auto_20160926_2341.py
press_releases/migrations/0005_auto_20161110_1531.py
press_releases/migrations/__init__.py
press_releases/templates/icekit_press_releases/pressrelease/layouts/default.html
press_releases/templates/icekit_press_releases/pressreleaselisting/layouts/default.html
