Metadata-Version: 2.0
Name: icekit-press-releases
Version: 0.81
Summary: A simple app to implement general-purpose Press Releases in ICEkit projects.
Home-page: https://github.com/ic-labs/icekit-press-releases
Author: Interaction Consortium
Author-email: studio@interaction.net.au
License: MIT
Platform: UNKNOWN
Requires-Dist: coverage
Requires-Dist: django-icekit
Provides-Extra: dev
Requires-Dist: ipdb; extra == 'dev'
Requires-Dist: ipython; extra == 'dev'
Provides-Extra: postgres
Requires-Dist: psycopg2; extra == 'postgres'
Provides-Extra: testing
Requires-Dist: mock; extra == 'testing'
Requires-Dist: requests; extra == 'testing'
